flaresolverr-3.3.21rc4.post2.dist-info/METADATA
flaresolverr-3.3.21rc4.post2.dist-info/WHEEL
flaresolverr-3.3.21rc4.post2.dist-info/licenses/LICENSE
flaresolverr/__init__.py
flaresolverr/__main__.py
flaresolverr/bottle_plugins/__init__.py
flaresolverr/bottle_plugins/error_plugin.py
flaresolverr/bottle_plugins/logger_plugin.py
flaresolverr/bottle_plugins/prometheus_plugin.py
flaresolverr/build_package.py
flaresolverr/dtos.py
flaresolverr/flaresolverr.py
flaresolverr/flaresolverr_service.py
flaresolverr/metrics.py
flaresolverr/resources/package.json
flaresolverr/sessions.py
flaresolverr/tests.py
flaresolverr/tests_sites.py
flaresolverr/utils.py
flaresolverr-3.3.21rc4.post2.dist-info/RECORD
