Metadata-Version: 2.1
Name: FlareSolverr
Version: 3.3.21rc4.post2
Summary: Proxy server to bypass Cloudflare protection
Keywords: proxy,cloudflare,ddos-guard,captcha,security
Home-page: https://github.com/FlareSolverr/FlareSolverr/
Author-Email: Diego Heras <ngosang@hotmail.es>
Maintainer-Email: Paul Pfeister <code@pfeister.dev>
License: MIT
Classifier: Development Status :: 5 - Production/Stable
Classifier: Environment :: Console
Classifier: Intended Audience :: Developers
Classifier: License :: OSI Approved :: MIT License
Classifier: Programming Language :: Python :: 3
Classifier: Programming Language :: Python :: 3.9
Classifier: Programming Language :: Python :: 3.10
Classifier: Programming Language :: Python :: 3.11
Classifier: Programming Language :: Python :: 3.12
Project-URL: Homepage, https://github.com/FlareSolverr/FlareSolverr/
Project-URL: Bug-tracker, https://github.com/FlareSolverr/FlareSolverr/issues/
Project-URL: Documentation, https://github.com/FlareSolverr/FlareSolverr/wiki/
Requires-Python: >=3.9
Requires-Dist: bottle==0.12.25
Requires-Dist: waitress==2.1.2
Requires-Dist: DrissionPage==4.1.0.0b14
Requires-Dist: func-timeout==4.3.5
Requires-Dist: prometheus-client==0.17.1
Requires-Dist: requests==2.32.0
Requires-Dist: certifi==2024.07.04
Requires-Dist: websockets==11.0.3
Requires-Dist: xvfbwrapper==0.2.9; platform_system != "Windows"
Requires-Dist: pefile==2023.2.7; platform_system == "Windows"
Requires-Dist: urllib3>=2.2.2
Requires-Dist: idna>=3.7
